graph2gnn/__init__.py
graph2gnn/exceptions.py
graph2gnn/tiger2gnn.py
graph2gnn-0.0.2.dist-info/METADATA
graph2gnn-0.0.2.dist-info/WHEEL
graph2gnn-0.0.2.dist-info/licenses/LICENSE
graph2gnn-0.0.2.dist-info/licenses/NOTICE.txt
graph2gnn-0.0.2.dist-info/RECORD
